bball_api/__init__.py
bball_api-0.1.2.dist-info/METADATA
bball_api-0.1.2.dist-info/WHEEL
bball_api-0.1.2.dist-info/RECORD
